MANIFEST.in
README.rst
setup.py
tomcom/__init__.py
tomcom.bootstrap.navbar.egg-info/PKG-INFO
tomcom.bootstrap.navbar.egg-info/SOURCES.txt
tomcom.bootstrap.navbar.egg-info/dependency_links.txt
tomcom.bootstrap.navbar.egg-info/entry_points.txt
tomcom.bootstrap.navbar.egg-info/namespace_packages.txt
tomcom.bootstrap.navbar.egg-info/not-zip-safe
tomcom.bootstrap.navbar.egg-info/requires.txt
tomcom.bootstrap.navbar.egg-info/top_level.txt
tomcom/bootstrap/__init__.py
tomcom/bootstrap/navbar/__init__.py
tomcom/bootstrap/navbar/configure.zcml
tomcom/bootstrap/navbar/browser/__init__.py
tomcom/bootstrap/navbar/browser/configure.zcml
tomcom/bootstrap/navbar/browser/tcbnavbar/__init__.py
tomcom/bootstrap/navbar/browser/tcbnavbar/browser.py
tomcom/bootstrap/navbar/browser/tcbnavbar/configure.zcml
tomcom/bootstrap/navbar/browser/tcbnavbar/templates/tcb_navbar.pt
tomcom/bootstrap/navbar/tests/__init__.py
tomcom/bootstrap/navbar/tests/test_tcbnavbar.py