Metadata-Version: 1.1
Name: tomcom.bootstrap.navbar
Version: 4.3.0.0
Summary: Navbar build fron portal_actions in bootstrap style
Home-page: http://stash.tomcom.de/scm/PLONE/tomcom.bootstrap.navbar.git
Author: tomcom GmbH
Author-email: mailto:info@tomcom.de
License: GPL2
Keywords: tomcom plone
Platform: UNKNOWN
Classifier: Framework :: Plone
Classifier: Framework :: Plone :: 4.3
Classifier: Programming Language :: Python
Classifier: Topic :: Software Development :: Libraries :: Python Modules
